pyrealsense2/__init__.py
pyrealsense2/pyrealdds.cp311-win_amd64.pyd
pyrealsense2/pyrealsense2.cp311-win_amd64.pyd
pyrealsense2/pyrsutils.cp311-win_amd64.pyd
pyrealsense2-2.56.0.8431.dist-info/METADATA
pyrealsense2-2.56.0.8431.dist-info/WHEEL
pyrealsense2-2.56.0.8431.dist-info/licenses/LICENSE
pyrealsense2-2.56.0.8431.dist-info/RECORD
